<?xml version="1.0" encoding="utf-8"?>
<!--DO NOT EDIT. This document is generated by PSoC Creator design builds.-->
<PSoCCreatorIdeExport Version="1">
  <Device Part="CY8C4125AZI-473" Processor="CortexM0" DeviceID="42B1193" />
  <Toolchains>
    <Toolchain Name="ARM GCC Generic" Selected="True">
      <Tool Name="prebuild" Command="" Options="" />
      <Tool Name="assembler" Command="arm-none-eabi-as.exe" Options="-mcpu=cortex-m0 -mthumb -I. -IGenerated_Source\PSoC4 -alh=${OutputDir}/${CompileFile}.lst -g -W" />
      <Tool Name="compiler" Command="arm-none-eabi-gcc.exe" Options="-mcpu=cortex-m0 -mthumb -I. -I..\..\qp_5.1\include -I..\..\qp_5.1\ports\arm-cm\vanilla\gnu -I..\..\nlib_psoc4 -I..\..\nlib_shared -I. -IGenerated_Source\PSoC4 -Wa,-alh=${OutputDir}/${CompileFile}.lst -g -D DEBUG -D CY_CORE_ID=0 -Wall -ffunction-sections -ffat-lto-objects -Og" />
      <Tool Name="linker" Command="arm-none-eabi-gcc.exe" Options="-mcpu=cortex-m0 -mthumb -l qp_cortex-m0_cr -l m -L Generated_Source\PSoC4 -L ..\..\qp_5.1\ports\arm-cm\vanilla\gnu\rel -Wl,-Map,${OutputDir}/${ProjectShortName}.map -T Generated_Source\PSoC4\cm0gcc.ld -specs=nano.specs -Wl,--gc-sections -u _printf_float -g -ffunction-sections -Og -ffat-lto-objects" />
      <Tool Name="postbuild" Command="" Options="" />
    </Toolchain>
    <Toolchain Name="ARM MDK Generic" Selected="False">
      <Tool Name="prebuild" Command="" Options="" />
      <Tool Name="assembler" Command="armasm.exe" Options="--cpu=Cortex-M0 --diag_style=gnu --thumb -i. -iGenerated_Source\PSoC4 -g --list=${OutputDir}/${CompileFile}.lst &quot;--predefine=__MICROLIB SETA 1&quot;" />
      <Tool Name="compiler" Command="armcc.exe" Options="--cpu=Cortex-M0 --C99 --diag_style=gnu -I. -IGenerated_Source\PSoC4 --list --signed_chars -g -D DEBUG -D CY_CORE_ID=0 -O0 --split_sections -D__MICROLIB" />
      <Tool Name="linker" Command="armlink.exe" Options="--cpu=Cortex-M0 --diag_style=gnu --no_startup --library_type=microlib --map --list ${OutputDir}/${ProjectShortName}.map --scatter Generated_Source\PSoC4\Cm0RealView.scat" />
      <Tool Name="postbuild" Command="" Options="" />
    </Toolchain>
    <Toolchain Name="ARM IAR Generic" Selected="False">
      <Tool Name="prebuild" Command="" Options="" />
      <Tool Name="assembler" Command="iasmarm.exe" Options="--cpu Cortex-M0 -I. -IGenerated_Source\PSoC4 -s+ -M&lt;&gt; -w+ -r -DDEBUG --fpu None" />
      <Tool Name="compiler" Command="iccarm.exe" Options="--cpu Cortex-M0 -I. -IGenerated_Source\PSoC4 -D DEBUG -D CY_CORE_ID=0 -I. -IGenerated_Source\PSoC4 -D DEBUG -D CY_CORE_ID=0 --no_cse --no_unroll --no_inline --no_code_motion --no_tbaa --no_clustering --no_scheduling --debug --endian=little -e --fpu=None -On --no_wrap_diagnostics" />
      <Tool Name="linker" Command="ilinkarm.exe" Options="--semihosting --entry __iar_program_start --config Generated_Source\PSoC4\Cm0Iar.icf" />
      <Tool Name="postbuild" Command="" Options="" />
    </Toolchain>
  </Toolchains>
  <Project Name="sound_lure" Path="C:\Users\jc497413\Desktop\psoc_photo_off\sound_lure_v1\sound_lure.cydsn" Version="5.70" Type="Normal">
    <CMSIS_SVD_File>sound_lure.svd</CMSIS_SVD_File>
    <Datasheet />
    <LinkerFiles>
      <LinkerFile Toolchain="ARM GCC Generic">.\Generated_Source\PSoC4\cm0gcc.ld</LinkerFile>
      <LinkerFile Toolchain="ARM MDK Generic">.\Generated_Source\PSoC4\Cm0RealView.scat</LinkerFile>
      <LinkerFile Toolchain="ARM IAR Generic">.\Generated_Source\PSoC4\Cm0Iar.icf</LinkerFile>
    </LinkerFiles>
    <Folders>
      <Folder BuildType="STRICT" Path="C:\Users\jc497413\Desktop\psoc_photo_off\sound_lure_v1\sound_lure.cydsn">
        <Files Root="C:\Users\jc497413\Desktop\psoc_photo_off\sound_lure_v1\sound_lure.cydsn">
          <File BuildType="BUILD" Toolchain="">main.c</File>
          <File BuildType="BUILD" Toolchain="">bsp.c</File>
          <File BuildType="BUILD" Toolchain="">mainFsm.c</File>
          <File BuildType="BUILD" Toolchain="">ucmd.c</File>
          <File BuildType="BUILD" Toolchain="">..\..\nlib_shared\nlib_assert.c</File>
          <File BuildType="BUILD" Toolchain="">..\..\nlib_shared\nlib_cproc.c</File>
          <File BuildType="BUILD" Toolchain="">..\..\nlib_shared\nlib_cstring_circbuf.c</File>
          <File BuildType="BUILD" Toolchain="">..\..\nlib_shared\nlib_cstring.c</File>
          <File BuildType="BUILD" Toolchain="">..\..\nlib_shared\nlib_btn.c</File>
          <File BuildType="BUILD" Toolchain="">..\..\nlib_shared\nlib_btnqp.c</File>
          <File BuildType="BUILD" Toolchain="">cyapicallbacks.h</File>
          <File BuildType="BUILD" Toolchain="">bsp.h</File>
          <File BuildType="BUILD" Toolchain="">dev.h</File>
          <File BuildType="BUILD" Toolchain="">ucmd.h</File>
          <File BuildType="BUILD" Toolchain="">..\..\nlib_shared\nlib_assert.h</File>
          <File BuildType="BUILD" Toolchain="">..\..\nlib_shared\nlib_cproc.h</File>
          <File BuildType="BUILD" Toolchain="">..\..\nlib_shared\nlib_sys_conv.h</File>
          <File BuildType="BUILD" Toolchain="">..\..\nlib_shared\nlib_cstring_circbuf.h</File>
          <File BuildType="BUILD" Toolchain="">..\..\nlib_shared\nlib_cstring.h</File>
          <File BuildType="BUILD" Toolchain="">..\..\nlib_shared\nlib_btn.h</File>
          <File BuildType="BUILD" Toolchain="">..\..\nlib_shared\nlib_btnqp.h</File>
        </Files>
      </Folder>
      <Folder BuildType="STRICT" Path="C:\Users\jc497413\Desktop\psoc_photo_off\sound_lure_v1\sound_lure.cydsn\Generated_Source\PSoC4">
        <Files Root="C:\Users\jc497413\Desktop\psoc_photo_off\sound_lure_v1\sound_lure.cydsn">
          <File BuildType="BUILD" Toolchain="">Generated_Source\PSoC4\cyfitter_cfg.h</File>
          <File BuildType="BUILD" Toolchain="">Generated_Source\PSoC4\cyfitter_cfg.c</File>
          <File BuildType="BUILD" Toolchain="">Generated_Source\PSoC4\cymetadata.c</File>
          <File BuildType="BUILD" Toolchain="">Generated_Source\PSoC4\cydevice_trm.h</File>
          <File BuildType="BUILD" Toolchain="">Generated_Source\PSoC4\cydevicegnu_trm.inc</File>
          <File BuildType="BUILD" Toolchain="">Generated_Source\PSoC4\cydevicerv_trm.inc</File>
          <File BuildType="BUILD" Toolchain="">Generated_Source\PSoC4\cydeviceiar_trm.inc</File>
          <File BuildType="BUILD" Toolchain="">Generated_Source\PSoC4\cyfittergnu.inc</File>
          <File BuildType="BUILD" Toolchain="">Generated_Source\PSoC4\cyfitterrv.inc</File>
          <File BuildType="BUILD" Toolchain="">Generated_Source\PSoC4\cyfitteriar.inc</File>
          <File BuildType="BUILD" Toolchain="">Generated_Source\PSoC4\CyPeripheralMaster.c</File>
          <File BuildType="BUILD" Toolchain="">Generated_Source\PSoC4\CyPeripheralMaster.h</File>
          <File BuildType="BUILD" Toolchain="">Generated_Source\PSoC4\CyDebounceMaster.c</File>
          <File BuildType="BUILD" Toolchain="">Generated_Source\PSoC4\CyDebounceMaster.h</File>
          <File BuildType="BUILD" Toolchain="">Generated_Source\PSoC4\cyfitter.h</File>
          <File BuildType="BUILD" Toolchain="">Generated_Source\PSoC4\cydisabledsheets.h</File>
          <File BuildType="BUILD" Toolchain="">Generated_Source\PSoC4\DetectBuf.c</File>
          <File BuildType="BUILD" Toolchain="">Generated_Source\PSoC4\DetectBuf.h</File>
          <File BuildType="BUILD" Toolchain="">Generated_Source\PSoC4\DetectBuf_PM.c</File>
          <File BuildType="BUILD" Toolchain="">Generated_Source\PSoC4\DbgUart.c</File>
          <File BuildType="BUILD" Toolchain="">Generated_Source\PSoC4\DbgUart.h</File>
          <File BuildType="BUILD" Toolchain="">Generated_Source\PSoC4\DbgUart_SPI_UART.h</File>
          <File BuildType="BUILD" Toolchain="">Generated_Source\PSoC4\DbgUart_SPI_UART.c</File>
          <File BuildType="BUILD" Toolchain="">Generated_Source\PSoC4\DbgUart_SPI_UART_INT.c</File>
          <File BuildType="BUILD" Toolchain="">Generated_Source\PSoC4\DbgUart_PM.c</File>
          <File BuildType="BUILD" Toolchain="">Generated_Source\PSoC4\DbgUart_UART.c</File>
          <File BuildType="BUILD" Toolchain="">Generated_Source\PSoC4\DbgUart_BOOT.c</File>
          <File BuildType="BUILD" Toolchain="">Generated_Source\PSoC4\DbgUart_UART_BOOT.c</File>
          <File BuildType="BUILD" Toolchain="">Generated_Source\PSoC4\DbgUart_PINS.h</File>
          <File BuildType="BUILD" Toolchain="">Generated_Source\PSoC4\DbgUart_SPI_UART_PVT.h</File>
          <File BuildType="BUILD" Toolchain="">Generated_Source\PSoC4\DbgUart_PVT.h</File>
          <File BuildType="BUILD" Toolchain="">Generated_Source\PSoC4\DbgUart_BOOT.h</File>
          <File BuildType="BUILD" Toolchain="">Generated_Source\PSoC4\SineOut.c</File>
          <File BuildType="BUILD" Toolchain="">Generated_Source\PSoC4\SineOut.h</File>
          <File BuildType="BUILD" Toolchain="">Generated_Source\PSoC4\SineOut_aliases.h</File>
          <File BuildType="BUILD" Toolchain="">Generated_Source\PSoC4\SineOut_PM.c</File>
          <File BuildType="BUILD" Toolchain="">Generated_Source\PSoC4\LightDetect.c</File>
          <File BuildType="BUILD" Toolchain="">Generated_Source\PSoC4\LightDetect.h</File>
          <File BuildType="BUILD" Toolchain="">Generated_Source\PSoC4\LightDetect_aliases.h</File>
          <File BuildType="BUILD" Toolchain="">Generated_Source\PSoC4\LightDetect_PM.c</File>
          <File BuildType="BUILD" Toolchain="">Generated_Source\PSoC4\SquareTimer.c</File>
          <File BuildType="BUILD" Toolchain="">Generated_Source\PSoC4\SquareTimer.h</File>
          <File BuildType="BUILD" Toolchain="">Generated_Source\PSoC4\SquareTimer_PM.c</File>
          <File BuildType="BUILD" Toolchain="">Generated_Source\PSoC4\SquareGen.c</File>
          <File BuildType="BUILD" Toolchain="">Generated_Source\PSoC4\SquareGen.h</File>
          <File BuildType="BUILD" Toolchain="">Generated_Source\PSoC4\SquareGen_PM.c</File>
          <File BuildType="BUILD" Toolchain="">Generated_Source\PSoC4\BattDetectEn.c</File>
          <File BuildType="BUILD" Toolchain="">Generated_Source\PSoC4\BattDetectEn.h</File>
          <File BuildType="BUILD" Toolchain="">Generated_Source\PSoC4\BattDetectEn_aliases.h</File>
          <File BuildType="BUILD" Toolchain="">Generated_Source\PSoC4\BattDetectEn_PM.c</File>
          <File BuildType="BUILD" Toolchain="">Generated_Source\PSoC4\SAR.c</File>
          <File BuildType="BUILD" Toolchain="">Generated_Source\PSoC4\SAR.h</File>
          <File BuildType="BUILD" Toolchain="">Generated_Source\PSoC4\SAR_PM.c</File>
          <File BuildType="BUILD" Toolchain="">Generated_Source\PSoC4\SAR_INT.c</File>
          <File BuildType="BUILD" Toolchain="">Generated_Source\PSoC4\BattDetect.c</File>
          <File BuildType="BUILD" Toolchain="">Generated_Source\PSoC4\BattDetect.h</File>
          <File BuildType="BUILD" Toolchain="">Generated_Source\PSoC4\BattDetect_aliases.h</File>
          <File BuildType="BUILD" Toolchain="">Generated_Source\PSoC4\BattDetect_PM.c</File>
          <File BuildType="BUILD" Toolchain="">Generated_Source\PSoC4\LightDetectEn.c</File>
          <File BuildType="BUILD" Toolchain="">Generated_Source\PSoC4\LightDetectEn.h</File>
          <File BuildType="BUILD" Toolchain="">Generated_Source\PSoC4\LightDetectEn_aliases.h</File>
          <File BuildType="BUILD" Toolchain="">Generated_Source\PSoC4\LightDetectEn_PM.c</File>
          <File BuildType="BUILD" Toolchain="">Generated_Source\PSoC4\SineGenBuf.c</File>
          <File BuildType="BUILD" Toolchain="">Generated_Source\PSoC4\SineGenBuf.h</File>
          <File BuildType="BUILD" Toolchain="">Generated_Source\PSoC4\SineGenBuf_PM.c</File>
          <File BuildType="BUILD" Toolchain="">Generated_Source\PSoC4\Btn_Int.c</File>
          <File BuildType="BUILD" Toolchain="">Generated_Source\PSoC4\Btn_Int.h</File>
          <File BuildType="BUILD" Toolchain="">Generated_Source\PSoC4\SineGenFb.c</File>
          <File BuildType="BUILD" Toolchain="">Generated_Source\PSoC4\SineGenFb.h</File>
          <File BuildType="BUILD" Toolchain="">Generated_Source\PSoC4\SineGenFb_aliases.h</File>
          <File BuildType="BUILD" Toolchain="">Generated_Source\PSoC4\SineGenFb_PM.c</File>
          <File BuildType="BUILD" Toolchain="">Generated_Source\PSoC4\SineGenBufIn.c</File>
          <File BuildType="BUILD" Toolchain="">Generated_Source\PSoC4\SineGenBufIn.h</File>
          <File BuildType="BUILD" Toolchain="">Generated_Source\PSoC4\SineGenBufIn_aliases.h</File>
          <File BuildType="BUILD" Toolchain="">Generated_Source\PSoC4\SineGenBufIn_PM.c</File>
          <File BuildType="BUILD" Toolchain="">Generated_Source\PSoC4\DetectMux.c</File>
          <File BuildType="BUILD" Toolchain="">Generated_Source\PSoC4\DetectMux.h</File>
          <File BuildType="BUILD" Toolchain="">Generated_Source\PSoC4\SineGenOut.c</File>
          <File BuildType="BUILD" Toolchain="">Generated_Source\PSoC4\SineGenOut.h</File>
          <File BuildType="BUILD" Toolchain="">Generated_Source\PSoC4\SineGenOut_aliases.h</File>
          <File BuildType="BUILD" Toolchain="">Generated_Source\PSoC4\SineGenOut_PM.c</File>
          <File BuildType="BUILD" Toolchain="">Generated_Source\PSoC4\LED_LOWBATT.c</File>
          <File BuildType="BUILD" Toolchain="">Generated_Source\PSoC4\LED_LOWBATT.h</File>
          <File BuildType="BUILD" Toolchain="">Generated_Source\PSoC4\LED_LOWBATT_aliases.h</File>
          <File BuildType="BUILD" Toolchain="">Generated_Source\PSoC4\LED_LOWBATT_PM.c</File>
          <File BuildType="BUILD" Toolchain="">Generated_Source\PSoC4\LED_LOWLIGHT.c</File>
          <File BuildType="BUILD" Toolchain="">Generated_Source\PSoC4\LED_LOWLIGHT.h</File>
          <File BuildType="BUILD" Toolchain="">Generated_Source\PSoC4\LED_LOWLIGHT_aliases.h</File>
          <File BuildType="BUILD" Toolchain="">Generated_Source\PSoC4\LED_LOWLIGHT_PM.c</File>
          <File BuildType="BUILD" Toolchain="">Generated_Source\PSoC4\LED_DEVICEON.c</File>
          <File BuildType="BUILD" Toolchain="">Generated_Source\PSoC4\LED_DEVICEON.h</File>
          <File BuildType="BUILD" Toolchain="">Generated_Source\PSoC4\LED_DEVICEON_aliases.h</File>
          <File BuildType="BUILD" Toolchain="">Generated_Source\PSoC4\LED_DEVICEON_PM.c</File>
          <File BuildType="BUILD" Toolchain="">Generated_Source\PSoC4\LED_SPKRON.c</File>
          <File BuildType="BUILD" Toolchain="">Generated_Source\PSoC4\LED_SPKRON.h</File>
          <File BuildType="BUILD" Toolchain="">Generated_Source\PSoC4\LED_SPKRON_aliases.h</File>
          <File BuildType="BUILD" Toolchain="">Generated_Source\PSoC4\LED_SPKRON_PM.c</File>
          <File BuildType="BUILD" Toolchain="">Generated_Source\PSoC4\BOOST_SHDN_B.c</File>
          <File BuildType="BUILD" Toolchain="">Generated_Source\PSoC4\BOOST_SHDN_B.h</File>
          <File BuildType="BUILD" Toolchain="">Generated_Source\PSoC4\BOOST_SHDN_B_aliases.h</File>
          <File BuildType="BUILD" Toolchain="">Generated_Source\PSoC4\BOOST_SHDN_B_PM.c</File>
          <File BuildType="BUILD" Toolchain="">Generated_Source\PSoC4\SPKR_SHDN_B.c</File>
          <File BuildType="BUILD" Toolchain="">Generated_Source\PSoC4\SPKR_SHDN_B.h</File>
          <File BuildType="BUILD" Toolchain="">Generated_Source\PSoC4\SPKR_SHDN_B_aliases.h</File>
          <File BuildType="BUILD" Toolchain="">Generated_Source\PSoC4\SPKR_SHDN_B_PM.c</File>
          <File BuildType="BUILD" Toolchain="">Generated_Source\PSoC4\SPKR_GAIN.c</File>
          <File BuildType="BUILD" Toolchain="">Generated_Source\PSoC4\SPKR_GAIN.h</File>
          <File BuildType="BUILD" Toolchain="">Generated_Source\PSoC4\SPKR_GAIN_aliases.h</File>
          <File BuildType="BUILD" Toolchain="">Generated_Source\PSoC4\SPKR_GAIN_PM.c</File>
          <File BuildType="BUILD" Toolchain="">Generated_Source\PSoC4\DbgUartTx.c</File>
          <File BuildType="BUILD" Toolchain="">Generated_Source\PSoC4\DbgUartTx.h</File>
          <File BuildType="BUILD" Toolchain="">Generated_Source\PSoC4\DbgUartTx_aliases.h</File>
          <File BuildType="BUILD" Toolchain="">Generated_Source\PSoC4\DbgUartTx_PM.c</File>
          <File BuildType="BUILD" Toolchain="">Generated_Source\PSoC4\DbgUartRx.c</File>
          <File BuildType="BUILD" Toolchain="">Generated_Source\PSoC4\DbgUartRx.h</File>
          <File BuildType="BUILD" Toolchain="">Generated_Source\PSoC4\DbgUartRx_aliases.h</File>
          <File BuildType="BUILD" Toolchain="">Generated_Source\PSoC4\DbgUartRx_PM.c</File>
          <File BuildType="BUILD" Toolchain="">Generated_Source\PSoC4\DbgUartRx_Int.c</File>
          <File BuildType="BUILD" Toolchain="">Generated_Source\PSoC4\DbgUartRx_Int.h</File>
          <File BuildType="BUILD" Toolchain="">Generated_Source\PSoC4\PeriodicCheck_Int.c</File>
          <File BuildType="BUILD" Toolchain="">Generated_Source\PSoC4\PeriodicCheck_Int.h</File>
          <File BuildType="BUILD" Toolchain="">Generated_Source\PSoC4\Btn.c</File>
          <File BuildType="BUILD" Toolchain="">Generated_Source\PSoC4\Btn.h</File>
          <File BuildType="BUILD" Toolchain="">Generated_Source\PSoC4\Btn_aliases.h</File>
          <File BuildType="BUILD" Toolchain="">Generated_Source\PSoC4\Btn_PM.c</File>
          <File BuildType="BUILD" Toolchain="">Generated_Source\PSoC4\DbgUart_SCBCLK.c</File>
          <File BuildType="BUILD" Toolchain="">Generated_Source\PSoC4\DbgUart_SCBCLK.h</File>
          <File BuildType="BUILD" Toolchain="">Generated_Source\PSoC4\SAR_IRQ.c</File>
          <File BuildType="BUILD" Toolchain="">Generated_Source\PSoC4\SAR_IRQ.h</File>
          <File BuildType="BUILD" Toolchain="">Generated_Source\PSoC4\SAR_intClock.c</File>
          <File BuildType="BUILD" Toolchain="">Generated_Source\PSoC4\SAR_intClock.h</File>
          <File BuildType="BUILD" Toolchain="ARM GCC Generic">Generated_Source\PSoC4\cm0gcc.ld</File>
          <File BuildType="BUILD" Toolchain="ARM MDK Generic">Generated_Source\PSoC4\Cm0RealView.scat</File>
          <File BuildType="BUILD" Toolchain="">Generated_Source\PSoC4\Cm0Start.c</File>
          <File BuildType="BUILD" Toolchain="">Generated_Source\PSoC4\core_cm0.h</File>
          <File BuildType="BUILD" Toolchain="">Generated_Source\PSoC4\core_cm0_psoc4.h</File>
          <File BuildType="BUILD" Toolchain="ARM MDK Generic">Generated_Source\PSoC4\CyBootAsmRv.s</File>
          <File BuildType="BUILD" Toolchain="">Generated_Source\PSoC4\CyFlash.c</File>
          <File BuildType="BUILD" Toolchain="">Generated_Source\PSoC4\CyFlash.h</File>
          <File BuildType="BUILD" Toolchain="">Generated_Source\PSoC4\CyLib.c</File>
          <File BuildType="BUILD" Toolchain="">Generated_Source\PSoC4\CyLib.h</File>
          <File BuildType="BUILD" Toolchain="">Generated_Source\PSoC4\cyPm.c</File>
          <File BuildType="BUILD" Toolchain="">Generated_Source\PSoC4\cyPm.h</File>
          <File BuildType="BUILD" Toolchain="">Generated_Source\PSoC4\cytypes.h</File>
          <File BuildType="BUILD" Toolchain="">Generated_Source\PSoC4\cyutils.c</File>
          <File BuildType="BUILD" Toolchain="">Generated_Source\PSoC4\cypins.h</File>
          <File BuildType="BUILD" Toolchain="">Generated_Source\PSoC4\core_cmFunc.h</File>
          <File BuildType="BUILD" Toolchain="">Generated_Source\PSoC4\core_cmInstr.h</File>
          <File BuildType="BUILD" Toolchain="ARM IAR Generic">Generated_Source\PSoC4\Cm0Iar.icf</File>
          <File BuildType="BUILD" Toolchain="ARM IAR Generic">Generated_Source\PSoC4\CyBootAsmIar.s</File>
          <File BuildType="BUILD" Toolchain="">Generated_Source\PSoC4\cmsis_armcc.h</File>
          <File BuildType="BUILD" Toolchain="">Generated_Source\PSoC4\cmsis_gcc.h</File>
          <File BuildType="BUILD" Toolchain="">Generated_Source\PSoC4\cmsis_compiler.h</File>
          <File BuildType="BUILD" Toolchain="ARM GCC Generic">Generated_Source\PSoC4\CyBootAsmGnu.s</File>
          <File BuildType="BUILD" Toolchain="">Generated_Source\PSoC4\CyLFClk.c</File>
          <File BuildType="BUILD" Toolchain="">Generated_Source\PSoC4\CyLFClk.h</File>
          <File BuildType="BUILD" Toolchain="">Generated_Source\PSoC4\cy_em_eeprom.c</File>
          <File BuildType="BUILD" Toolchain="">Generated_Source\PSoC4\cy_em_eeprom.h</File>
          <File BuildType="BUILD" Toolchain="">Generated_Source\PSoC4\project.h</File>
          <File BuildType="BUILD" Toolchain="">Generated_Source\PSoC4\cycodeshareimport.ld</File>
          <File BuildType="BUILD" Toolchain="">Generated_Source\PSoC4\cycodeshareexport.ld</File>
          <File BuildType="BUILD" Toolchain="">Generated_Source\PSoC4\cycodeshareimport.scat</File>
          <File BuildType="BUILD" Toolchain="">Generated_Source\PSoC4\TimerOnOff.c</File>
          <File BuildType="BUILD" Toolchain="">Generated_Source\PSoC4\TimerOnOff.h</File>
          <File BuildType="BUILD" Toolchain="">Generated_Source\PSoC4\TimerOnOff_PM.c</File>
          <File BuildType="BUILD" Toolchain="">Generated_Source\PSoC4\Clock_3.c</File>
          <File BuildType="BUILD" Toolchain="">Generated_Source\PSoC4\Clock_3.h</File>
          <File BuildType="BUILD" Toolchain="">Generated_Source\PSoC4\SpeakerPause_Int.c</File>
          <File BuildType="BUILD" Toolchain="">Generated_Source\PSoC4\SpeakerPause_Int.h</File>
        </Files>
      </Folder>
      <Folder BuildType="EXCLUDE" Path=".\codegentemp">
        <Files Root="C:\Users\jc497413\Desktop\psoc_photo_off\sound_lure_v1\sound_lure.cydsn" />
      </Folder>
      <Folder BuildType="EXCLUDE" Path=".\ARM_GCC_441">
        <Files Root="C:\Users\jc497413\Desktop\psoc_photo_off\sound_lure_v1\sound_lure.cydsn" />
      </Folder>
      <Folder BuildType="EXCLUDE" Path=".\ARM_GCC_473">
        <Files Root="C:\Users\jc497413\Desktop\psoc_photo_off\sound_lure_v1\sound_lure.cydsn" />
      </Folder>
      <Folder BuildType="EXCLUDE" Path=".\DP8051_Keil_952">
        <Files Root="C:\Users\jc497413\Desktop\psoc_photo_off\sound_lure_v1\sound_lure.cydsn" />
      </Folder>
      <Folder BuildType="EXCLUDE" Path=".\DP8051">
        <Files Root="C:\Users\jc497413\Desktop\psoc_photo_off\sound_lure_v1\sound_lure.cydsn" />
      </Folder>
      <Folder BuildType="EXCLUDE" Path=".\CortexM0">
        <Files Root="C:\Users\jc497413\Desktop\psoc_photo_off\sound_lure_v1\sound_lure.cydsn" />
      </Folder>
      <Folder BuildType="EXCLUDE" Path=".\CortexM0p">
        <Files Root="C:\Users\jc497413\Desktop\psoc_photo_off\sound_lure_v1\sound_lure.cydsn" />
      </Folder>
      <Folder BuildType="EXCLUDE" Path=".\CortexM3">
        <Files Root="C:\Users\jc497413\Desktop\psoc_photo_off\sound_lure_v1\sound_lure.cydsn" />
      </Folder>
      <Folder BuildType="EXCLUDE" Path=".\CortexM4">
        <Files Root="C:\Users\jc497413\Desktop\psoc_photo_off\sound_lure_v1\sound_lure.cydsn" />
      </Folder>
      <Folder BuildType="EXCLUDE" Path=".\CortexM7">
        <Files Root="C:\Users\jc497413\Desktop\psoc_photo_off\sound_lure_v1\sound_lure.cydsn" />
      </Folder>
    </Folders>
  </Project>
</PSoCCreatorIdeExport>